puzzle_sim/__init__.py
puzzle_sim/adapters.py
puzzle_sim/helpers.py
puzzle_sim/models.py
puzzle_sim/py.typed
puzzle_sim/state_dict_converter/__init__.py
puzzle_sim/state_dict_converter/convnext_mapper.py
puzzle_sim/state_dict_converter/vit_mapper.py
puzzle_sim-1.0.1.dist-info/licenses/LICENSE.md
puzzle_sim-1.0.1.dist-info/METADATA
puzzle_sim-1.0.1.dist-info/WHEEL
puzzle_sim-1.0.1.dist-info/top_level.txt
puzzle_sim-1.0.1.dist-info/RECORD
