Metadata-Version: 2.4
Name: puzzle_sim
Version: 1.0.1
Summary: Implementation of PuzzleSim, a cross-refence image similarity metric designed for artifact detection in novel view synthesis methods.
Author-email: Nicolai Hermann <hermann.nicolai@gmail.com>, Jorge Condor <jorge.condor@usi.ch>, Piotr Didyk <piotr.didyk@usi.ch>
Maintainer-email: Nicolai Hermann <hermann.nicolai@gmail.com>
License: MIT License
Project-URL: Homepage, https://nihermann.github.io/puzzlesim/index.html
Project-URL: Repository, https://github.com/nihermann/PuzzleSim.git
Project-URL: Issues, https://github.com/nihermann/PuzzleSim/issues
Keywords: puzzle similarity,similarity,no reference,cross reference,image metric
Classifier: Development Status :: 5 - Production/Stable
Classifier: Programming Language :: Python :: 3
Classifier: Programming Language :: Python :: 3.8
Classifier: Programming Language :: Python :: 3.9
Classifier: Programming Language :: Python :: 3.10
Classifier: Programming Language :: Python :: 3.11
Classifier: Programming Language :: Python :: 3.12
Classifier: Operating System :: OS Independent
Requires-Python: >=3.8
License-File: LICENSE.md
Requires-Dist: torch
Requires-Dist: torchvision
Requires-Dist: matplotlib
Requires-Dist: pillow
Requires-Dist: torchmetrics
Requires-Dist: numpy
Requires-Dist: huggingface_hub[cli]
Requires-Dist: transformers
Requires-Dist: accelerate
Requires-Dist: termcolor
Provides-Extra: dev
Requires-Dist: pytest; extra == "dev"
Requires-Dist: mypy; extra == "dev"
Requires-Dist: hf_transfer; extra == "dev"
Dynamic: license-file
